{
  "KillAuraModes": "Nearest",
  "CPSMin": 12.0,
  "CPSMax": 17.0,
  "HeuristicsYaw": 5.0,
  "HeuristicsYaw2": 5.0,
  "HeuristicsPitch": 10.0,
  "HeuristicsPitch2": 10.0,
  "CorrectMM": false,
  "Heuristics": true,
  "GCD": true,
  "AutoBlockModes": "hypixel",
  "AutoBlock": true,
  "KeepSprinting": true,
  "DisableDeath": false,
  "AttackInInv": false,
  "Raycast": false,
  "Players": true,
  "Villagers": false,
  "Mobs": false,
  "Animals": false,
  "TargetESP": true,
  "TargetESPModes": "jello",
  "TargetESPRed": 0.0,
  "TargetESPGreen": 123.0,
  "TargetESPBlue": 122.0,
  "TargetESPAlpha": 255.0,
  "TargetESPRainbow": false,
  "KoksSpeed": 0.2767857142857143,
  "CritParticles": 5.0,
  "Range": 4.041666666666667,
  "AntiBotModes": "WatchDog",
  "AutoArmorDelay": 71.0,
  "OpenInvAutoArmor": false,
  "Criticals Mode": "Packet",
  "SplashHealth": 12.078125,
  "SplashDelay": 200.0,
  "SplashJump": true,
  "WatchDog": false,
  "Jump": false,
  "Auto Jump": false,
  "Render Cycle": true,
  "Radius": 4.2,
  "CycleRed": 0.0,
  "CycleGreen": 0.0,
  "CycleBlue": 0.0,
  "OnlyPlayers": true,
  "AutoShoot": true,
  "ThroughWalls": true,
  "MoveFix": false,
  "ClampYaw": false,
  "LockView": false,
  "Disabler Mode": "Hypixel",
  "Design": "Xave",
  "Sound": true,
  "GuiRed": 0.0,
  "GuiGreen": 0.0,
  "GuiBlue": 0.0,
  "Rainbow": false,
  "THUDMode": "novoline",
  "Rainbow Fade": true,
  "Theme": false,
  "StepMode": "Legit",
  "LagbackChecker": true,
  "SpeedMode": "hypixel",
  "TimerSpeed": 2.2,
  "Flight Mode": "hypixel",
  "FlightAni": false,
  "NoSlowModes": "hypixel",
  "NoFallMode": "normal",
  "LongJump Mode": "Hypixel",
  "AntiVoidModes": "flag",
  "StartDelay": 1000.0,
  "StealDelay": 239.0,
  "CloseChest": true,
  "UnlockMouse": false,
  "InvMove": false,
  "SilentSteal": false,
  "Delay": 71.0,
  "OpenInvInvManager": true,
  "AutoDisable": true,
  "CloseInvInvManager": false,
  "EatPackets": 1.0,
  "Velocity Modes": "Cancel",
  "Capes": "Trajan 1",
  "Cape": true,
  "Wings": true,
  "Wither": false,
  "WitherRed": 0.0,
  "WitherGreen": 124.0,
  "WitherBlue": 255.0,
  "WitherAlpha": 6.0,
  "Creeper": false,
  "CreeperRed": 0.0,
  "CreeperGreen": 0.0,
  "CreeperBlue": 0.0,
  "CreeperAlpha": 0.0,
  "Ghast": false,
  "SkinChange": false,
  "Skins": "shept",
  "HideSB": false,
  "HideChat": false,
  "ChinaRadius": 0.596875,
  "BlockAni": "spin",
  "SmoothS": true,
  "SwingSpeed": 6.010416666666667,
  "ItemX": 0.0,
  "ItemY": 0.25,
  "ItemZ": 0.0,
  "ItemSize": 0.20208333333333334,
  "Chest": true,
  "Ender": false,
  "ESPModes": "shader",
  "Bones": true,
  "SmoothBones": false,
  "ChamsColored": false,
  "ChamsTextured": false,
  "TrailWidth": 3.0,
  "TrailLength": 200.0,
  "PointCounter": 100.0,
  "RainbowTrail": true,
  "GlintRainbow": false,
  "OnlyEnchanted": true,
  "GlintRed": 0.0,
  "GlintGreen": 85.0,
  "GlintBlue": 255.0,
  "DayTime": 12.0,
  "Speed": false,
  "Silent": true,
  "SameYPos": false,
  "ScaffoldMode": "Hypixel",
  "Tower": false,
  "DownScaffold": false,
  "Diagonal": false,
  "Sprint": true,
  "SprintMode": "Post",
  "BlockA3Fix": false,
  "BlockMouse": false,
  "BlockPrediction": false,
  "BlockRandomAim": false,
  "BlockRandomPitch": false,
  "BlockClampYaw": true,
  "BlockSpeed": 180.0,
  "Fucker Modes": "Beds",
  "A3Fix": false,
  "BedMouse": false,
  "BedPrediction": false,
  "BedRandomAim": false,
  "BedRandomPitch": false,
  "BedClampYaw": true,
  "BedSpeed": 0.0,
  "LongJump": false,
  "Velocity": true,
  "EnchantmentGlint": true,
  "InstantRespawn": false,
  "MemoryCleaner": false,
  "MidClickFriends": false,
  "HealthManager": false,
  "InventoryMove": false,
  "StreamerMode": true,
  "WorldChanger": true,
  "MurderFinder": false,
  "Flight": false,
  "FlagDetector": false,
  "AutoRegister": false,
  "NoSlowdown": true,
  "ChestStealer": false,
  "ScaffoldWalk": false,
  "GamePurger": false,
  "NoRotateSet": false,
  "FriendReject": false,
  "ArmorStatus": false,
  "MotionGraph": true,
  "TargetStrafe": false,
  "ItemPhysics": true,
  "PartyAccept": false,
  "DisablePFAs": false,
  "InvManager": false,
  "Trajectories": true,
  "NoHurtCam": true,
  "AutoSplash": false,
  "BowAimbot": false,
  "KeyStrokes": false,
  "AutoArmor": false,
  "FastLadder": false,
  "AutoSword": false,
  "TargetHUD": true,
  "StairSpeed": false,
  "TNTRadius": true,
  "FastBridge": false,
  "BedFucker": false,
  "AntiVanish": false,
  "VerusAura": false,
  "Cosmetics": true,
  "NameTags": false,
  "NoFriends": false,
  "Animation": true,
  "AutoSoup": false,
  "TNTBlock": false,
  "ChinaESP": true,
  "Fullbright": false,
  "GodMode": false,
  "FastPlace": false,
  "ChestEsp": true,
  "Safewalk": false,
  "AutoHeal": false,
  "SuperHit": false,
  "Direction": false,
  "NewHUD": false,
  "ItemESP": false,
  "NoSwing": false,
  "AutoTool": true,
  "FastBow": false,
  "Disabler": true,
  "KillSults": false,
  "AntiVoid": false,
  "TrailESP": true,
  "Criticals": false,
  "Crasher": false,
  "ClickGui": false,
  "AutoEat": false,
  "KillAura": false,
  "Parkour": false,
  "LowFire": false,
  "AntiBot": true,
  "FastEat": false,
  "Tracers": true,
  "Minime": true,
  "NoWeb": false,
  "Hotbar": true,
  "Spider": false,
  "NoBob": true,
  "Teams": false,
  "Regen": false,
  "NoFall": false,
  "Strafe": false,
  "Phase": false,
  "Jesus": false,
  "Stats": false,
  "VClip": false,
  "Blink": false,
  "Step": false,
  "Zoot": false,
  "HUD": true,
  "ESP": true
}
